fpop/__about__.py
fpop/__init__.py
fpop/abacus.py
fpop/cp2k.py
fpop/prep_fp.py
fpop/preprun_fp.py
fpop/run_fp.py
fpop/vasp.py
fpop/utils/__init__.py
fpop/utils/step_config.py
tests/__init__.py
tests/constants.py
tests/context.py
tests/mocked_ops.py
tests/test_abacus_inputs.py
tests/test_cp2k_inputs.py
tests/test_prep_abacus.py
tests/test_prep_cp2k.py
tests/test_prep_run_vasp.py
tests/test_prep_vasp.py
tests/test_run_abacus.py
tests/test_run_cp2k.py
tests/test_run_fp.py
tests/test_run_vasp.py
tests/test_vasp_inputs.py
fpop-0.0.8.dist-info/LICENSE
fpop-0.0.8.dist-info/METADATA
fpop-0.0.8.dist-info/WHEEL
fpop-0.0.8.dist-info/top_level.txt
fpop-0.0.8.dist-info/RECORD
