Metadata-Version: 2.1
Name: fpop
Version: 0.0.8
Summary: Operators related to first-principles calculation
Home-page: https://github.com/deepmodeling/fpop
Author: Chengqian Zhang
Author-email: 2043899742@qq.com
Classifier: Programming Language :: Python :: 3
Classifier: License :: OSI Approved :: GNU Lesser General Public License v3 (LGPLv3)
Classifier: Operating System :: OS Independent
Provides: fpop
Requires-Python: >=3.7
License-File: LICENSE
Requires-Dist: pydflow
Requires-Dist: lbg
Requires-Dist: dpdata
Requires-Dist: numpy
Requires-Dist: ase
Requires-Dist: dargs
